LICENSE
fsai_file_split/__init__.py
fsai_file_split/main.py
fsai_file_split/split_libs/jsonl_split.py
fsai_file_split-0.1.2.dist-info/entry_points.txt
fsai_file_split-0.1.2.dist-info/LICENSE
fsai_file_split-0.1.2.dist-info/WHEEL
fsai_file_split-0.1.2.dist-info/METADATA
fsai_file_split-0.1.2.dist-info/RECORD
